remotemanager/__init__.py
remotemanager/JUBEInterop/JUBEInterop.py
remotemanager/JUBEInterop/__init__.py
remotemanager/connection/__init__.py
remotemanager/connection/cmd.py
remotemanager/connection/computer.py
remotemanager/connection/testing_object.py
remotemanager/connection/url.py
remotemanager/connection/validate_error.py
remotemanager/dataset/__init__.py
remotemanager/dataset/dataset.py
remotemanager/dataset/dataset_mixin.py
remotemanager/dataset/dependency.py
remotemanager/dataset/files_mixin.py
remotemanager/dataset/function_generation.py
remotemanager/dataset/lazy_append.py
remotemanager/dataset/repo.py
remotemanager/dataset/runner.py
remotemanager/dataset/runnerstates.py
remotemanager/dataset/summary_instance.py
remotemanager/decorators/__init__.py
remotemanager/decorators/magic.py
remotemanager/decorators/remotefunction.py
remotemanager/decorators/sanzufunction.py
remotemanager/script/__init__.py
remotemanager/script/delayvar.py
remotemanager/script/get_pragma.py
remotemanager/script/script.py
remotemanager/script/substitution.py
remotemanager/script/utils.py
remotemanager/serialisation/__init__.py
remotemanager/serialisation/serial.py
remotemanager/serialisation/serialdill.py
remotemanager/serialisation/serialjson.py
remotemanager/serialisation/serialjsonpickle.py
remotemanager/serialisation/serialyaml.py
remotemanager/storage/__init__.py
remotemanager/storage/database.py
remotemanager/storage/function.py
remotemanager/storage/sendablemixin.py
remotemanager/storage/trackedfile.py
remotemanager/transport/__init__.py
remotemanager/transport/cp.py
remotemanager/transport/rsync.py
remotemanager/transport/scp.py
remotemanager/transport/transport.py
remotemanager/utils/__init__.py
remotemanager/utils/basetestclass.py
remotemanager/utils/confirm.py
remotemanager/utils/count_fstring_variables.py
remotemanager/utils/flags.py
remotemanager/utils/format_iterable.py
remotemanager/utils/log.py
remotemanager/utils/tokenizer.py
remotemanager/utils/url_helpers.py
remotemanager-0.14.2.dist-info/licenses/LICENSE
remotemanager-0.14.2.dist-info/METADATA
remotemanager-0.14.2.dist-info/WHEEL
remotemanager-0.14.2.dist-info/top_level.txt
remotemanager-0.14.2.dist-info/RECORD
