Metadata-Version: 2.4
Name: remotemanager
Version: 0.14.2
Summary: remote run management tool
Author-email: Louis Beal <louis.j.beal@gmail.com>
Project-URL: Homepage, https://gitlab.com/l_sim/remotemanager/
Project-URL: Documentation, https://l_sim.gitlab.io/remotemanager/
Project-URL: Repository, https://gitlab.com/l_sim/remotemanager/
Project-URL: Issues, https://gitlab.com/l_sim/remotemanager/-/issues
Project-URL: Changelog, https://l_sim.gitlab.io/remotemanager/versions.html
Keywords: HPC,remote,scheduler,workflow,workflows,distributed
Classifier: License :: OSI Approved :: MIT License
Classifier: Programming Language :: Python :: 3.7
Classifier: Programming Language :: Python :: 3.8
Classifier: Programming Language :: Python :: 3.9
Classifier: Programming Language :: Python :: 3.10
Classifier: Programming Language :: Python :: 3.11
Classifier: Programming Language :: Python :: 3.12
Classifier: Operating System :: OS Independent
Classifier: Topic :: Scientific/Engineering
Classifier: Topic :: System :: Benchmark
Classifier: Topic :: System :: Distributed Computing
Requires-Python: >=3.7
License-File: LICENSE
Requires-Dist: pyyaml
Requires-Dist: requests
Requires-Dist: typing_extensions
Provides-Extra: dill
Requires-Dist: dill; extra == "dill"
Provides-Extra: jsonpickle
Requires-Dist: jsonpickle; extra == "jsonpickle"
Provides-Extra: all
Requires-Dist: dill; extra == "all"
Requires-Dist: jsonpickle; extra == "all"
Provides-Extra: docs
Requires-Dist: nbsphinx; extra == "docs"
Requires-Dist: sphinx-rtd-theme; extra == "docs"
Requires-Dist: furo; extra == "docs"
Provides-Extra: dev
Requires-Dist: dill; extra == "dev"
Requires-Dist: jsonpickle; extra == "dev"
Requires-Dist: sphinx; extra == "dev"
Requires-Dist: nbsphinx; extra == "dev"
Requires-Dist: sphinx-rtd-theme; extra == "dev"
Requires-Dist: pytest; extra == "dev"
Requires-Dist: pytest-cov; extra == "dev"
Requires-Dist: pytest-xdist; extra == "dev"
Requires-Dist: psutil; extra == "dev"
Requires-Dist: nbval; extra == "dev"
Requires-Dist: bumpver; extra == "dev"
Requires-Dist: numpy; extra == "dev"
Requires-Dist: ruff; extra == "dev"
Requires-Dist: furo; extra == "dev"
Requires-Dist: pre-commit; extra == "dev"
Dynamic: license-file
